hwcramerchecker/.DS_Store
hwcramerchecker/__init__.py
hwcramerchecker/hwcramerchecker.py
hwcramerchecker_py-1.1.0.dist-info/METADATA
hwcramerchecker_py-1.1.0.dist-info/WHEEL
hwcramerchecker_py-1.1.0.dist-info/RECORD
